geotils/__init__.py
geotils/data_processing/__init__.py
geotils/data_processing/augmentation.py
geotils/data_processing/cropping.py
geotils/data_processing/data_processing_utils.py
geotils/data_processing/make_dataset.py
geotils/data_processing/masker.py
geotils/data_processing/polygon_utility.py
geotils/data_processing/post_process.py
geotils/data_processing/resizing.py
geotils/data_processing/splitting.py
geotils/data_processing/tile_utils.py
geotils/data_processing/transform_coordinates.py
geotils/data_processing/pre_processing/Datum_Transform.py
geotils/data_processing/pre_processing/Mosaic.py
geotils/data_processing/pre_processing/batch.py
geotils/data_processing/pre_processing/masking.py
geotils/data_processing/pre_processing/pansharp.py
geotils/data_processing/pre_processing/pre_processing.py
geotils/datasets/Geobase.py
geotils/datasets/Geotorch_datasets.py
geotils/datasets/__init__.py
geotils/datasets/examples/__init__.py
geotils/datasets/examples/georeferneced/Massachusetts_Buildings_Dataset.py
geotils/datasets/examples/nongeoreferenced/vlm.py
geotils/datasets/old_dataset_classes/FloodNet_Dataset.py
geotils/datasets/old_dataset_classes/Planet_Dataset_reader.py
geotils/datasets/old_dataset_classes/data_loader.py
geotils/datasets/old_dataset_classes/sentinel_1_reader.py
geotils/datasets/old_dataset_classes/sentinel_2_reader.py
geotils/evaluation/__init__.py
geotils/evaluation/evaluate.py
geotils/evaluation/meters.py
geotils/evaluation/metrics.py
geotils/evaluation/tmp.py
geotils/logging/__init__.py
geotils/logging/configuration.py
geotils/logging/test_configuration.py
geotils/losses/__init__.py
geotils/losses/losses.py
geotils/losses/lovasz.py
geotils/models/ASPP.py
geotils/models/OCR.py
geotils/models/RA_modules.py
geotils/models/Unet_W_Mods.py
geotils/models/__init__.py
geotils/models/pred_SAM.py
geotils/optimizers/__init__.py
geotils/optimizers/adamw.py
geotils/optimizers/test_optimizer.py
geotils/optimizers/over9000/__init__.py
geotils-0.3.0.post2.dist-info/LICENSE.txt
geotils-0.3.0.post2.dist-info/METADATA
geotils-0.3.0.post2.dist-info/WHEEL
geotils-0.3.0.post2.dist-info/entry_points.txt
geotils-0.3.0.post2.dist-info/top_level.txt
geotils-0.3.0.post2.dist-info/RECORD
