Metadata-Version: 2.1
Name: geotils
Version: 0.3.0.post2
Summary: geotils by GEOAI group
Author-email: GEOAI group <geotils@geogroup.ai>
Maintainer-email: GEOAI group <geotils@geogroup.ai>
Project-URL: Homepage, https://geogroup.ai/
Project-URL: Documentation, https://readthedocs.org/geotils
Project-URL: Repository, https://github.com/geoaigroup/geotils
Project-URL: Bug Tracker, https://github.com/geoaigroup/geotils/issues
Project-URL: Changelog, https://github.com/geoaigroup/geotils/blob/master/CHANGELOG.md
Keywords: geotils,geospatial,earth observation
Classifier: Development Status :: 3 - Alpha
Classifier: Intended Audience :: Developers
Classifier: Topic :: Software Development :: Build Tools
Classifier: License :: OSI Approved :: MIT License
Classifier: Programming Language :: Python
Requires-Python: >=3.10
License-File: LICENSE.txt
Requires-Dist: numpy ==1.26.1
Requires-Dist: geopandas ==0.14.4
Requires-Dist: shapely ==2.0.4
Requires-Dist: scikit-learn ==1.5.0
Requires-Dist: tabulate ==0.9.0
Requires-Dist: timm ==0.9.2
Requires-Dist: torchvision ==0.18.1
Requires-Dist: rasterio ==1.3.10
Requires-Dist: scikit-image ==0.24.0
Requires-Dist: matplotlib ==3.9.0
Requires-Dist: affine ==2.4.0
Requires-Dist: opencv-python ==4.10.0.84
Requires-Dist: simplification ==0.7.10
Requires-Dist: imantics ==0.1.12
Requires-Dist: torchgeo ==0.5.2
Requires-Dist: segmentation-models-pytorch ==0.3.3
Requires-Dist: pystac ==1.10.1
Requires-Dist: mercantile ==1.2.1
Requires-Dist: supermercado ==0.2.0
Requires-Dist: scipy ==1.13.1
Requires-Dist: fiona ==1.9.6
Requires-Dist: pandas ==2.2.2
Requires-Dist: pillow ==10.3.0
Requires-Dist: tifffile ==2023.9.26
Requires-Dist: tqdm ==4.66.4
Requires-Dist: albumentations ==1.3.1
Requires-Dist: opencv-python-headless ==4.8.1.78
Requires-Dist: seaborn ==0.13.1
Requires-Dist: icecream ==2.1.3
